aloha/__init__.py
aloha/assets/bimanual_viperx_end_effector_insertion.xml
aloha/assets/bimanual_viperx_end_effector_transfer_cube.xml
aloha/assets/bimanual_viperx_insertion.xml
aloha/assets/bimanual_viperx_transfer_cube.xml
aloha/assets/scene.xml
aloha/assets/tabletop.stl
aloha/assets/vx300s_10_custom_finger_left.stl
aloha/assets/vx300s_10_custom_finger_right.stl
aloha/assets/vx300s_10_gripper_finger.stl
aloha/assets/vx300s_11_ar_tag.stl
aloha/assets/vx300s_1_base.stl
aloha/assets/vx300s_2_shoulder.stl
aloha/assets/vx300s_3_upper_arm.stl
aloha/assets/vx300s_4_upper_forearm.stl
aloha/assets/vx300s_5_lower_forearm.stl
aloha/assets/vx300s_6_wrist.stl
aloha/assets/vx300s_7_gripper.stl
aloha/assets/vx300s_8_gripper_prop.stl
aloha/assets/vx300s_9_gripper_bar.stl
aloha/assets/vx300s_dependencies.xml
aloha/assets/vx300s_left.xml
aloha/assets/vx300s_right.xml
aloha/constants.py
aloha/env.py
aloha/tasks/sim.py
aloha/tasks/sim_end_effector.py
aloha/utils.py
sim_aloha-0.1.2.dist-info/METADATA
sim_aloha-0.1.2.dist-info/WHEEL
sim_aloha-0.1.2.dist-info/RECORD
